Metadata-Version: 2.1
Name: lr-for-the-masses-SamV01
Version: 1.0.0
Summary: The purpose of this package is to provide simplified tools to apply several different linear regression models
Home-page: https://github.com/samuel-velez/533_lab_4_KatheVelez
Author: Samuel Vélez and Mandar Kathe 
Author-email: samuelvelez@outlook.com
License: UNKNOWN
Platform: UNKNOWN
Classifier: Programming Language :: Python :: 3
Classifier: License :: OSI Approved :: MIT License
Classifier: Operating System :: OS Independent
Requires-Python: >=3.5
